jgb_editor/__init__.py
jgb_editor/__main__.py
jgb_editor/jeonggan.py
jgb_editor/key_mapping.json
jgb_editor/load_xml.py
jgb_editor/main.py
jgb_editor/pitch_etc_name.py
jgb_editor/pitch_name.py
jgb_editor/save_xml.py
jgb_editor/style.css
jgb_editor/__pycache__/__init__.cpython-310.pyc
jgb_editor/__pycache__/__main__.cpython-310.pyc
jgb_editor/__pycache__/__main__.cpython-38.pyc
jgb_editor/__pycache__/jeonggan.cpython-310.pyc
jgb_editor/__pycache__/load_xml.cpython-310.pyc
jgb_editor/__pycache__/main.cpython-310.pyc
jgb_editor/__pycache__/pitch_etc_name.cpython-310.pyc
jgb_editor/__pycache__/pitch_name.cpython-310.pyc
jgb_editor/__pycache__/save_xml.cpython-310.pyc
jgb_editor/image/exit.svg
jgb_editor/image/export.svg
jgb_editor/image/logo.ico
jgb_editor/image/logo.png
jgb_editor/image/new.svg
jgb_editor/image/open.svg
jgb_editor/image/save.svg
jgb_editor/image/save_as.svg
jgb_editor/image/sumpyo1.bmp
jgb_editor/image/sumpyo1.png
jgb_editor/image/sumpyo2.bmp
jgb_editor/image/sumpyo2.png
jgb_editor/image/sumpyo2_down.png
jgb_editor/image/sumpyo3.bmp
jgb_editor/image/jangsikeum/naneuna.png
jgb_editor/image/jangsikeum/nanina.png
jgb_editor/image/jangsikeum/nanireu.png
jgb_editor/image/jangsikeum/neone.png
jgb_editor/image/jangsikeum/neunireu.png
jgb_editor/image/jangsikeum/neuronireu.png
jgb_editor/image/jangsikeum/ni.png
jgb_editor/image/jangsikeum/nina.png
jgb_editor/image/jangsikeum/nira.png
jgb_editor/image/jangsikeum/nire.png
jgb_editor/image/jangsikeum/no.png
jgb_editor/image/jangsikeum/none.png
jgb_editor/image/jangsikeum/noniro.png
jgb_editor/image/jangsikeum/ri.png
jgb_editor/image/jangsikeum/ro.png
jgb_editor/image/sigimsae/araero_ddeoneun_pyo.png
jgb_editor/image/sigimsae/araero_ddeoneun_pyo_bottom.png
jgb_editor/image/sigimsae/gyop_heullim_pyo.png
jgb_editor/image/sigimsae/gyop_mineun_pyo.png
jgb_editor/image/sigimsae/heullim_pyo1.png
jgb_editor/image/sigimsae/heullim_pyo2.png
jgb_editor/image/sigimsae/heullim_pyo2_bottom.png
jgb_editor-1.1.3.dist-info/LICENSE
jgb_editor-1.1.3.dist-info/METADATA
jgb_editor-1.1.3.dist-info/WHEEL
jgb_editor-1.1.3.dist-info/entry_points.txt
jgb_editor-1.1.3.dist-info/top_level.txt
jgb_editor-1.1.3.dist-info/RECORD
