Metadata-Version: 2.1
Name: jgb-editor
Version: 1.1.3
Summary: 간단한 정간보 편집기 / a simple Jeongganbo editor
Home-page: https://github.com/depth221/Jeongganbo-editor
Author: Hwang Dongha
Author-email: depth221@gmail.com
License: GPLV3+
Classifier: Programming Language :: Python :: 3
Classifier: Programming Language :: Python :: 3.9
Classifier: Programming Language :: Python :: 3.10
Classifier: Programming Language :: Python :: 3.11
Classifier: Programming Language :: Python :: 3.12
Classifier: Programming Language :: Python :: 3.13
Classifier: License :: OSI Approved :: GNU General Public License v3 or later (GPLv3+)
Classifier: Operating System :: OS Independent
Requires-Python: >=3.9
License-File: LICENSE
Requires-Dist: pyqt5 ~=5.15.7
Requires-Dist: beautifulsoup4 ~=4.12.2
